moomoolah/__init__.py
moomoolah/__main__.py
moomoolah/budget_app.py
moomoolah/config.py
moomoolah/state.py
moomoolah/style.css
moomoolah/widgets.py
moomoolah-0.3.0.dist-info/METADATA
moomoolah-0.3.0.dist-info/WHEEL
moomoolah-0.3.0.dist-info/entry_points.txt
moomoolah-0.3.0.dist-info/licenses/LICENSE
moomoolah-0.3.0.dist-info/RECORD
