Metadata-Version: 2.4
Name: moomoolah
Version: 0.3.0
Summary: MooMoolah - Personal Budget Planner
Author-email: Elias Dorneles <elias.dorneles@hey.com>
License-Expression: MIT
License-File: LICENSE
Keywords: budget,personal-finance,textual,tui
Classifier: Development Status :: 3 - Alpha
Classifier: Environment :: Console
Classifier: Intended Audience :: End Users/Desktop
Classifier: License :: OSI Approved :: MIT License
Classifier: Operating System :: OS Independent
Classifier: Programming Language :: Python :: 3
Classifier: Programming Language :: Python :: 3.11
Classifier: Programming Language :: Python :: 3.12
Classifier: Topic :: Office/Business :: Financial
Requires-Python: >=3.11
Requires-Dist: pydantic>=2.6.3
Requires-Dist: python-dateutil>=2.9.0
Requires-Dist: textual>=0.52.1
Provides-Extra: dev
Requires-Dist: ipython>=8.22.1; extra == 'dev'
Requires-Dist: isort>=5.13.2; extra == 'dev'
Requires-Dist: pytest>=8.0.2; extra == 'dev'
Requires-Dist: textual-dev>=1.5.1; extra == 'dev'
